{
  "headerId": 73,
  "unknown1": 15,
  "matrixId": 162,
  "scriptFileId": 80,
  "levelScriptId": 580,
  "textArchiveId": 93,
  "musicDayId": 1068,
  "musicNightId": 1068,
  "wildPokemon": 65535,
  "eventFileId": 72,
  "locationNameId": 122,
  "areaIcon": 6,
  "weatherId": 0,
  "cameraAngleId": 4,
  "showNameTagId": 4,
  "battleBackground": 7,
  "canUseFly": false,
  "canUseRope": false,
  "canUseRun": false,
  "canUseBicycle": false,
  "locationName": "Galaktik-Gebäude",
  "showNameTag": false
}